setup.cfg
setup.py
yapyautotest/__init__.py
yapyautotest/autotest.py
yapyautotest/filefilter.py
yapyautotest/importutil.py
yapyautotest/mapper.py
yapyautotest/runner.py
yapyautotest.egg-info/PKG-INFO
yapyautotest.egg-info/SOURCES.txt
yapyautotest.egg-info/dependency_links.txt
yapyautotest.egg-info/entry_points.txt
yapyautotest.egg-info/requires.txt
yapyautotest.egg-info/top_level.txt