Metadata-Version: 1.0
Name: yapyautotest
Version: 0.6
Summary: Automatically run tests when files are modified.
Home-page: https://github.com/dnephin/PyAutoTest
Author: Daniel Nephin
Author-email: dnephin@gmail.com
License: UNKNOWN
Platform: UNKNOWN
